group_decomposition/.DS_Store
group_decomposition/__init__.py
group_decomposition/fg_query.py
group_decomposition/fragfunctions.py
group_decomposition/utils.py
group_decomposition-0.6.1.dist-info/LICENSE
group_decomposition-0.6.1.dist-info/WHEEL
group_decomposition-0.6.1.dist-info/METADATA
group_decomposition-0.6.1.dist-info/RECORD
