Metadata-Version: 2.1
Name: group_decomposition
Version: 0.6.1
Summary: A plugin for extracting data from .sum files and manipuating them
Keywords: qtaim,functional groups
Author-email: Kevin Lefrancois-Gagnon <kgagnon@lakeheadu.ca>, Robert Mawhinney <mawhinn@lakeheadu.ca>
Requires-Python: >=3.10
Classifier: Programming Language :: Python
Classifier: Programming Language :: Python :: 3
Classifier: Programming Language :: Python :: 3.10
Classifier: Programming Language :: Python :: 3.11
Classifier: Intended Audience :: Science/Research
Classifier: License :: OSI Approved :: MIT License
Classifier: Natural Language :: English
Classifier: Development Status :: 3 - Alpha
Classifier: Framework :: AiiDA
Requires-Dist: numpy
Requires-Dist: pandas
Requires-Dist: rdkit
Requires-Dist: sphinx ; extra == "docs"
Requires-Dist: sphinxcontrib-contentui ; extra == "docs"
Requires-Dist: sphinxcontrib-details-directive ; extra == "docs"
Requires-Dist: sphinx-rtd-theme ; extra == "docs"
Requires-Dist: furo ; extra == "docs"
Requires-Dist: markupsafe<2.1 ; extra == "docs"
Requires-Dist: pandas ; extra == "docs"
Requires-Dist: numpy ; extra == "docs"
Requires-Dist: rdkit ; extra == "docs"
Requires-Dist: pre-commit~=2.2 ; extra == "pre-commit"
Requires-Dist: pylint~=2.15.10 ; extra == "pre-commit"
Requires-Dist: rdkit ; extra == "pre-commit"
Requires-Dist: pgtest~=1.3.1 ; extra == "testing"
Requires-Dist: wheel~=0.31 ; extra == "testing"
Requires-Dist: coverage ; extra == "testing"
Requires-Dist: pytest~=6.0 ; extra == "testing"
Requires-Dist: pytest-cov ; extra == "testing"
Requires-Dist: pytest-regressions~=2.3 ; extra == "testing"
Requires-Dist: rdkit ; extra == "testing"
Requires-Dist: coveralls ; extra == "testing"
Project-URL: Source, https://github.com/kmlefran/group_decomposition
Provides-Extra: docs
Provides-Extra: pre-commit
Provides-Extra: testing
